{
  "version": "0.2.0",
  "description": "Oxmgr is a lightweight, cross-platform process manager.",
  "homepage": "https://github.com/Vladimir-Urik/OxMgr",
  "license": "MIT",
  "architecture": {
    "64bit": {
      "url": "https://github.com/Vladimir-Urik/OxMgr/releases/download/v0.2.0/oxmgr-v0.2.0-x86_64-pc-windows-msvc.zip",
      "hash": "d2ca326a2b05c57304ac0f149ce780371adc6a58e2acce7aa846b02cc48a7cfc"
    }
  },
  "bin": "oxmgr.exe",
  "checkver": {
    "github": "Vladimir-Urik/OxMgr"
  },
  "autoupdate": {
    "architecture": {
      "64bit": {
        "url": "https://github.com/Vladimir-Urik/OxMgr/releases/download/v$version/oxmgr-v$version-x86_64-pc-windows-msvc.zip"
      }
    }
  }
}
